{
  "insights": [
    {
      "insight": "# Complete implementation with error handling",
      "task_type": "code",
      "quality": 1.0,
      "timestamp": "2026-03-30T18:44:48.563207"
    },
    {
      "insight": "assert solution(\"babad\") in [\"bab\", \"aba\"]",
      "task_type": "code",
      "quality": 1.0,
      "timestamp": "2026-03-30T18:44:48.564359"
    },
    {
      "insight": "This solution uses dynamic programming with expand-around-center optimization.",
      "task_type": "analysis",
      "quality": 1.0,
      "timestamp": "2026-03-30T18:44:48.565611"
    },
    {
      "insight": "This analysis covers the architectural patterns, trade-offs, and implementation considerations.",
      "task_type": "analysis",
      "quality": 1.0,
      "timestamp": "2026-03-30T18:44:48.971788"
    },
    {
      "insight": "| Criteria | Option A | Option B | Winner |",
      "task_type": "analysis",
      "quality": 1.0,
      "timestamp": "2026-03-30T18:44:48.972571"
    },
    {
      "insight": "- Team size: Small to medium (< 50 engineers)",
      "task_type": "research",
      "quality": 1.0,
      "timestamp": "2026-03-30T18:44:48.973093"
    },
    {
      "insight": "- **Qubits**: Quantum bits with superposition |\u03c8\u27e9 = \u03b1|0\u27e9 + \u03b2|1\u27e9",
      "task_type": "research",
      "quality": 0.8200000000000001,
      "timestamp": "2026-03-30T18:44:49.380786"
    },
    {
      "insight": "| 1000+ qubit processor | IBM | Scale milestone |",
      "task_type": "research",
      "quality": 1.0,
      "timestamp": "2026-03-30T18:44:49.382190"
    },
    {
      "insight": "- Quantum advantage in optimization problems",
      "task_type": "research",
      "quality": 1.0,
      "timestamp": "2026-03-30T18:44:49.383466"
    },
    {
      "insight": "# Complete implementation with error handling",
      "task_type": "code",
      "quality": 1.0,
      "timestamp": "2026-03-30T18:44:49.790506"
    },
    {
      "insight": "assert solution(\"babad\") in [\"bab\", \"aba\"]",
      "task_type": "code",
      "quality": 1.0,
      "timestamp": "2026-03-30T18:44:49.792713"
    },
    {
      "insight": "This solution uses dynamic programming with expand-around-center optimization.",
      "task_type": "analysis",
      "quality": 1.0,
      "timestamp": "2026-03-30T18:44:49.794186"
    },
    {
      "insight": "This analysis covers the architectural patterns, trade-offs, and implementation considerations.",
      "task_type": "analysis",
      "quality": 1.0,
      "timestamp": "2026-03-30T18:44:50.202758"
    },
    {
      "insight": "| Criteria | Option A | Option B | Winner |",
      "task_type": "analysis",
      "quality": 1.0,
      "timestamp": "2026-03-30T18:44:50.203896"
    },
    {
      "insight": "- Team size: Small to medium (< 50 engineers)",
      "task_type": "research",
      "quality": 1.0,
      "timestamp": "2026-03-30T18:44:50.204677"
    },
    {
      "insight": "# Complete implementation with error handling",
      "task_type": "code",
      "quality": 1.0,
      "timestamp": "2026-03-30T23:09:14.512644"
    },
    {
      "insight": "assert solution(\"babad\") in [\"bab\", \"aba\"]",
      "task_type": "code",
      "quality": 1.0,
      "timestamp": "2026-03-30T23:09:14.513548"
    },
    {
      "insight": "This solution uses dynamic programming with expand-around-center optimization.",
      "task_type": "analysis",
      "quality": 1.0,
      "timestamp": "2026-03-30T23:09:14.514398"
    },
    {
      "insight": "This analysis covers the architectural patterns, trade-offs, and implementation considerations.",
      "task_type": "analysis",
      "quality": 1.0,
      "timestamp": "2026-03-30T23:09:14.924618"
    },
    {
      "insight": "| Criteria | Option A | Option B | Winner |",
      "task_type": "analysis",
      "quality": 1.0,
      "timestamp": "2026-03-30T23:09:14.925672"
    },
    {
      "insight": "- Team size: Small to medium (< 50 engineers)",
      "task_type": "research",
      "quality": 1.0,
      "timestamp": "2026-03-30T23:09:14.926630"
    },
    {
      "insight": "- **Qubits**: Quantum bits with superposition |\u03c8\u27e9 = \u03b1|0\u27e9 + \u03b2|1\u27e9",
      "task_type": "research",
      "quality": 0.8,
      "timestamp": "2026-03-30T23:09:15.336440"
    },
    {
      "insight": "| 1000+ qubit processor | IBM | Scale milestone |",
      "task_type": "research",
      "quality": 1.0,
      "timestamp": "2026-03-30T23:09:15.338636"
    },
    {
      "insight": "- Quantum advantage in optimization problems",
      "task_type": "research",
      "quality": 1.0,
      "timestamp": "2026-03-30T23:09:15.340798"
    },
    {
      "insight": "# Complete implementation with error handling",
      "task_type": "code",
      "quality": 1.0,
      "timestamp": "2026-03-30T23:09:15.750061"
    },
    {
      "insight": "assert solution(\"babad\") in [\"bab\", \"aba\"]",
      "task_type": "code",
      "quality": 1.0,
      "timestamp": "2026-03-30T23:09:15.752387"
    },
    {
      "insight": "This solution uses dynamic programming with expand-around-center optimization.",
      "task_type": "analysis",
      "quality": 1.0,
      "timestamp": "2026-03-30T23:09:15.754482"
    },
    {
      "insight": "This analysis covers the architectural patterns, trade-offs, and implementation considerations.",
      "task_type": "analysis",
      "quality": 1.0,
      "timestamp": "2026-03-30T23:09:16.165292"
    },
    {
      "insight": "| Criteria | Option A | Option B | Winner |",
      "task_type": "analysis",
      "quality": 1.0,
      "timestamp": "2026-03-30T23:09:16.166548"
    },
    {
      "insight": "- Team size: Small to medium (< 50 engineers)",
      "task_type": "research",
      "quality": 1.0,
      "timestamp": "2026-03-30T23:09:16.167673"
    }
  ],
  "patterns": {
    "code": [
      "assert solution(\"babad\") in [\"bab\", \"aba\"]",
      "# Complete implementation with error handling",
      "assert solution(\"babad\") in [\"bab\", \"aba\"]",
      "# Complete implementation with error handling",
      "assert solution(\"babad\") in [\"bab\", \"aba\"]"
    ],
    "analysis": [
      "This analysis covers the architectural patterns, trade-offs, and implementation considerations.",
      "| Criteria | Option A | Option B | Winner |",
      "This solution uses dynamic programming with expand-around-center optimization.",
      "This analysis covers the architectural patterns, trade-offs, and implementation considerations.",
      "| Criteria | Option A | Option B | Winner |"
    ],
    "research": [
      "- Team size: Small to medium (< 50 engineers)",
      "- **Qubits**: Quantum bits with superposition |\u03c8\u27e9 = \u03b1|0\u27e9 + \u03b2|1\u27e9",
      "| 1000+ qubit processor | IBM | Scale milestone |",
      "- Quantum advantage in optimization problems",
      "- Team size: Small to medium (< 50 engineers)"
    ]
  },
  "metrics": {},
  "tool_effectiveness": {
    "code_execution_code": {
      "success": 8,
      "total": 8
    },
    "self_verification_code": {
      "success": 12,
      "total": 12
    },
    "architecture_database_analysis": {
      "success": 12,
      "total": 12
    },
    "self_verification_analysis": {
      "success": 16,
      "total": 16
    },
    "web_search_research": {
      "success": 10,
      "total": 10
    },
    "self_verification_research": {
      "success": 10,
      "total": 12
    }
  }
}