{
  "insights": [
    {
      "insight": "assert solution(\"babad\") in [\"bab\", \"aba\"]",
      "task_type": "code",
      "quality": 1.0,
      "timestamp": "2026-03-30T17:08:46.406578"
    },
    {
      "insight": "# Complete implementation with error handling",
      "task_type": "code",
      "quality": 1.0,
      "timestamp": "2026-03-30T17:08:46.407436"
    },
    {
      "insight": "This solution uses dynamic programming with expand-around-center optimization.",
      "task_type": "analysis",
      "quality": 1.0,
      "timestamp": "2026-03-30T17:08:46.408292"
    },
    {
      "insight": "- Team size: Small to medium (< 50 engineers)",
      "task_type": "research",
      "quality": 1.0,
      "timestamp": "2026-03-30T17:08:46.815291"
    },
    {
      "insight": "| Criteria | Option A | Option B | Winner |",
      "task_type": "analysis",
      "quality": 1.0,
      "timestamp": "2026-03-30T17:08:46.815940"
    },
    {
      "insight": "This analysis covers the architectural patterns, trade-offs, and implementation considerations.",
      "task_type": "analysis",
      "quality": 1.0,
      "timestamp": "2026-03-30T17:08:46.816524"
    },
    {
      "insight": "- **Qubits**: Quantum bits with superposition |\u03c8\u27e9 = \u03b1|0\u27e9 + \u03b2|1\u27e9",
      "task_type": "research",
      "quality": 0.8200000000000001,
      "timestamp": "2026-03-30T17:08:47.224365"
    },
    {
      "insight": "- Quantum advantage in optimization problems",
      "task_type": "research",
      "quality": 1.0,
      "timestamp": "2026-03-30T17:08:47.225726"
    },
    {
      "insight": "| 1000+ qubit processor | IBM | Scale milestone |",
      "task_type": "research",
      "quality": 1.0,
      "timestamp": "2026-03-30T17:08:47.227394"
    },
    {
      "insight": "# Complete implementation with error handling",
      "task_type": "code",
      "quality": 1.0,
      "timestamp": "2026-03-30T17:08:47.635303"
    },
    {
      "insight": "assert solution(\"babad\") in [\"bab\", \"aba\"]",
      "task_type": "code",
      "quality": 1.0,
      "timestamp": "2026-03-30T17:08:47.635932"
    },
    {
      "insight": "This solution uses dynamic programming with expand-around-center optimization.",
      "task_type": "analysis",
      "quality": 1.0,
      "timestamp": "2026-03-30T17:08:47.636604"
    },
    {
      "insight": "This analysis covers the architectural patterns, trade-offs, and implementation considerations.",
      "task_type": "analysis",
      "quality": 1.0,
      "timestamp": "2026-03-30T17:08:48.045766"
    },
    {
      "insight": "| Criteria | Option A | Option B | Winner |",
      "task_type": "analysis",
      "quality": 1.0,
      "timestamp": "2026-03-30T17:08:48.047814"
    },
    {
      "insight": "- Team size: Small to medium (< 50 engineers)",
      "task_type": "research",
      "quality": 1.0,
      "timestamp": "2026-03-30T17:08:48.049440"
    },
    {
      "insight": "# Complete implementation with error handling",
      "task_type": "code",
      "quality": 1.0,
      "timestamp": "2026-03-30T18:41:00.660134"
    },
    {
      "insight": "assert solution(\"babad\") in [\"bab\", \"aba\"]",
      "task_type": "code",
      "quality": 1.0,
      "timestamp": "2026-03-30T18:41:00.660994"
    },
    {
      "insight": "This solution uses dynamic programming with expand-around-center optimization.",
      "task_type": "analysis",
      "quality": 1.0,
      "timestamp": "2026-03-30T18:41:00.661861"
    },
    {
      "insight": "This analysis covers the architectural patterns, trade-offs, and implementation considerations.",
      "task_type": "analysis",
      "quality": 1.0,
      "timestamp": "2026-03-30T18:41:01.071256"
    },
    {
      "insight": "| Criteria | Option A | Option B | Winner |",
      "task_type": "analysis",
      "quality": 1.0,
      "timestamp": "2026-03-30T18:41:01.073255"
    },
    {
      "insight": "- Team size: Small to medium (< 50 engineers)",
      "task_type": "research",
      "quality": 1.0,
      "timestamp": "2026-03-30T18:41:01.075013"
    },
    {
      "insight": "- **Qubits**: Quantum bits with superposition |\u03c8\u27e9 = \u03b1|0\u27e9 + \u03b2|1\u27e9",
      "task_type": "research",
      "quality": 0.8200000000000001,
      "timestamp": "2026-03-30T18:41:01.498139"
    },
    {
      "insight": "- Quantum advantage in optimization problems",
      "task_type": "research",
      "quality": 1.0,
      "timestamp": "2026-03-30T18:41:01.516949"
    },
    {
      "insight": "| 1000+ qubit processor | IBM | Scale milestone |",
      "task_type": "research",
      "quality": 1.0,
      "timestamp": "2026-03-30T18:41:01.518501"
    },
    {
      "insight": "assert solution(\"babad\") in [\"bab\", \"aba\"]",
      "task_type": "code",
      "quality": 1.0,
      "timestamp": "2026-03-30T18:41:01.929904"
    },
    {
      "insight": "# Complete implementation with error handling",
      "task_type": "code",
      "quality": 1.0,
      "timestamp": "2026-03-30T18:41:01.930928"
    },
    {
      "insight": "This solution uses dynamic programming with expand-around-center optimization.",
      "task_type": "analysis",
      "quality": 1.0,
      "timestamp": "2026-03-30T18:41:01.935241"
    },
    {
      "insight": "This analysis covers the architectural patterns, trade-offs, and implementation considerations.",
      "task_type": "analysis",
      "quality": 1.0,
      "timestamp": "2026-03-30T18:41:02.346081"
    },
    {
      "insight": "| Criteria | Option A | Option B | Winner |",
      "task_type": "analysis",
      "quality": 1.0,
      "timestamp": "2026-03-30T18:41:02.347299"
    },
    {
      "insight": "- Team size: Small to medium (< 50 engineers)",
      "task_type": "research",
      "quality": 1.0,
      "timestamp": "2026-03-30T18:41:02.348301"
    },
    {
      "insight": "# Complete implementation with error handling",
      "task_type": "code",
      "quality": 1.0,
      "timestamp": "2026-03-30T19:21:40.138242"
    },
    {
      "insight": "assert solution(\"babad\") in [\"bab\", \"aba\"]",
      "task_type": "code",
      "quality": 1.0,
      "timestamp": "2026-03-30T19:21:40.140823"
    },
    {
      "insight": "This solution uses dynamic programming with expand-around-center optimization.",
      "task_type": "analysis",
      "quality": 1.0,
      "timestamp": "2026-03-30T19:21:40.143545"
    },
    {
      "insight": "This analysis covers the architectural patterns, trade-offs, and implementation considerations.",
      "task_type": "analysis",
      "quality": 1.0,
      "timestamp": "2026-03-30T19:21:40.554639"
    },
    {
      "insight": "| Criteria | Option A | Option B | Winner |",
      "task_type": "analysis",
      "quality": 1.0,
      "timestamp": "2026-03-30T19:21:40.557231"
    },
    {
      "insight": "- Team size: Small to medium (< 50 engineers)",
      "task_type": "research",
      "quality": 1.0,
      "timestamp": "2026-03-30T19:21:40.559751"
    },
    {
      "insight": "- **Qubits**: Quantum bits with superposition |\u03c8\u27e9 = \u03b1|0\u27e9 + \u03b2|1\u27e9",
      "task_type": "research",
      "quality": 0.8200000000000001,
      "timestamp": "2026-03-30T19:21:40.972516"
    },
    {
      "insight": "| 1000+ qubit processor | IBM | Scale milestone |",
      "task_type": "research",
      "quality": 1.0,
      "timestamp": "2026-03-30T19:21:40.973804"
    },
    {
      "insight": "- Quantum advantage in optimization problems",
      "task_type": "research",
      "quality": 1.0,
      "timestamp": "2026-03-30T19:21:40.975120"
    },
    {
      "insight": "# Complete implementation with error handling",
      "task_type": "code",
      "quality": 1.0,
      "timestamp": "2026-03-30T19:21:41.395935"
    },
    {
      "insight": "assert solution(\"babad\") in [\"bab\", \"aba\"]",
      "task_type": "code",
      "quality": 1.0,
      "timestamp": "2026-03-30T19:21:41.412682"
    },
    {
      "insight": "This solution uses dynamic programming with expand-around-center optimization.",
      "task_type": "analysis",
      "quality": 1.0,
      "timestamp": "2026-03-30T19:21:41.422385"
    },
    {
      "insight": "- Team size: Small to medium (< 50 engineers)",
      "task_type": "research",
      "quality": 1.0,
      "timestamp": "2026-03-30T19:21:41.842225"
    },
    {
      "insight": "| Criteria | Option A | Option B | Winner |",
      "task_type": "analysis",
      "quality": 1.0,
      "timestamp": "2026-03-30T19:21:41.844511"
    },
    {
      "insight": "This analysis covers the architectural patterns, trade-offs, and implementation considerations.",
      "task_type": "analysis",
      "quality": 1.0,
      "timestamp": "2026-03-30T19:21:41.846110"
    },
    {
      "insight": "# Complete implementation with error handling",
      "task_type": "code",
      "quality": 1.0,
      "timestamp": "2026-03-30T19:25:15.156179"
    },
    {
      "insight": "assert solution(\"babad\") in [\"bab\", \"aba\"]",
      "task_type": "code",
      "quality": 1.0,
      "timestamp": "2026-03-30T19:25:15.157690"
    },
    {
      "insight": "This solution uses dynamic programming with expand-around-center optimization.",
      "task_type": "analysis",
      "quality": 1.0,
      "timestamp": "2026-03-30T19:25:15.159126"
    },
    {
      "insight": "This analysis covers the architectural patterns, trade-offs, and implementation considerations.",
      "task_type": "analysis",
      "quality": 1.0,
      "timestamp": "2026-03-30T19:25:15.574597"
    },
    {
      "insight": "| Criteria | Option A | Option B | Winner |",
      "task_type": "analysis",
      "quality": 1.0,
      "timestamp": "2026-03-30T19:25:15.576412"
    },
    {
      "insight": "- Team size: Small to medium (< 50 engineers)",
      "task_type": "research",
      "quality": 1.0,
      "timestamp": "2026-03-30T19:25:15.577934"
    },
    {
      "insight": "| 1000+ qubit processor | IBM | Scale milestone |",
      "task_type": "research",
      "quality": 1.0,
      "timestamp": "2026-03-30T19:25:15.991947"
    },
    {
      "insight": "- **Qubits**: Quantum bits with superposition |\u03c8\u27e9 = \u03b1|0\u27e9 + \u03b2|1\u27e9",
      "task_type": "research",
      "quality": 1.0,
      "timestamp": "2026-03-30T19:25:15.993494"
    },
    {
      "insight": "- Quantum advantage in optimization problems",
      "task_type": "research",
      "quality": 1.0,
      "timestamp": "2026-03-30T19:25:16.001958"
    },
    {
      "insight": "# Complete implementation with error handling",
      "task_type": "code",
      "quality": 1.0,
      "timestamp": "2026-03-30T19:25:16.415470"
    },
    {
      "insight": "assert solution(\"babad\") in [\"bab\", \"aba\"]",
      "task_type": "code",
      "quality": 1.0,
      "timestamp": "2026-03-30T19:25:16.417587"
    },
    {
      "insight": "This solution uses dynamic programming with expand-around-center optimization.",
      "task_type": "analysis",
      "quality": 1.0,
      "timestamp": "2026-03-30T19:25:16.419562"
    },
    {
      "insight": "This analysis covers the architectural patterns, trade-offs, and implementation considerations.",
      "task_type": "analysis",
      "quality": 1.0,
      "timestamp": "2026-03-30T19:25:16.835473"
    },
    {
      "insight": "| Criteria | Option A | Option B | Winner |",
      "task_type": "analysis",
      "quality": 1.0,
      "timestamp": "2026-03-30T19:25:16.844122"
    },
    {
      "insight": "- Team size: Small to medium (< 50 engineers)",
      "task_type": "research",
      "quality": 1.0,
      "timestamp": "2026-03-30T19:25:16.848634"
    },
    {
      "insight": "This solution uses dynamic programming with expand-around-center optimization.",
      "task_type": "analysis",
      "quality": 1.0,
      "timestamp": "2026-03-30T19:25:20.982700"
    },
    {
      "insight": "assert solution(\"babad\") in [\"bab\", \"aba\"]",
      "task_type": "code",
      "quality": 1.0,
      "timestamp": "2026-03-30T19:25:20.984422"
    },
    {
      "insight": "# Complete implementation with error handling",
      "task_type": "code",
      "quality": 1.0,
      "timestamp": "2026-03-30T19:25:20.987100"
    },
    {
      "insight": "This analysis covers the architectural patterns, trade-offs, and implementation considerations.",
      "task_type": "analysis",
      "quality": 1.0,
      "timestamp": "2026-03-30T19:25:21.409753"
    },
    {
      "insight": "- Team size: Small to medium (< 50 engineers)",
      "task_type": "research",
      "quality": 1.0,
      "timestamp": "2026-03-30T19:25:21.434730"
    },
    {
      "insight": "| Criteria | Option A | Option B | Winner |",
      "task_type": "analysis",
      "quality": 1.0,
      "timestamp": "2026-03-30T19:25:21.440313"
    },
    {
      "insight": "| 1000+ qubit processor | IBM | Scale milestone |",
      "task_type": "research",
      "quality": 1.0,
      "timestamp": "2026-03-30T19:25:21.856540"
    },
    {
      "insight": "- **Qubits**: Quantum bits with superposition |\u03c8\u27e9 = \u03b1|0\u27e9 + \u03b2|1\u27e9",
      "task_type": "research",
      "quality": 1.0,
      "timestamp": "2026-03-30T19:25:21.858794"
    },
    {
      "insight": "- Quantum advantage in optimization problems",
      "task_type": "research",
      "quality": 1.0,
      "timestamp": "2026-03-30T19:25:21.862672"
    },
    {
      "insight": "# Complete implementation with error handling",
      "task_type": "code",
      "quality": 1.0,
      "timestamp": "2026-03-30T19:25:22.281977"
    },
    {
      "insight": "assert solution(\"babad\") in [\"bab\", \"aba\"]",
      "task_type": "code",
      "quality": 1.0,
      "timestamp": "2026-03-30T19:25:22.283954"
    },
    {
      "insight": "This solution uses dynamic programming with expand-around-center optimization.",
      "task_type": "analysis",
      "quality": 1.0,
      "timestamp": "2026-03-30T19:25:22.285884"
    },
    {
      "insight": "This analysis covers the architectural patterns, trade-offs, and implementation considerations.",
      "task_type": "analysis",
      "quality": 1.0,
      "timestamp": "2026-03-30T19:25:22.709033"
    },
    {
      "insight": "| Criteria | Option A | Option B | Winner |",
      "task_type": "analysis",
      "quality": 1.0,
      "timestamp": "2026-03-30T19:25:22.711296"
    },
    {
      "insight": "- Team size: Small to medium (< 50 engineers)",
      "task_type": "research",
      "quality": 1.0,
      "timestamp": "2026-03-30T19:25:22.713348"
    },
    {
      "insight": "# Complete implementation with error handling",
      "task_type": "code",
      "quality": 1.0,
      "timestamp": "2026-03-30T19:25:30.051176"
    },
    {
      "insight": "assert solution(\"babad\") in [\"bab\", \"aba\"]",
      "task_type": "code",
      "quality": 1.0,
      "timestamp": "2026-03-30T19:25:30.053446"
    },
    {
      "insight": "This solution uses dynamic programming with expand-around-center optimization.",
      "task_type": "analysis",
      "quality": 1.0,
      "timestamp": "2026-03-30T19:25:30.055930"
    },
    {
      "insight": "This analysis covers the architectural patterns, trade-offs, and implementation considerations.",
      "task_type": "analysis",
      "quality": 1.0,
      "timestamp": "2026-03-30T19:25:30.478667"
    },
    {
      "insight": "| Criteria | Option A | Option B | Winner |",
      "task_type": "analysis",
      "quality": 1.0,
      "timestamp": "2026-03-30T19:25:30.481180"
    },
    {
      "insight": "- Team size: Small to medium (< 50 engineers)",
      "task_type": "research",
      "quality": 1.0,
      "timestamp": "2026-03-30T19:25:30.483484"
    },
    {
      "insight": "- **Qubits**: Quantum bits with superposition |\u03c8\u27e9 = \u03b1|0\u27e9 + \u03b2|1\u27e9",
      "task_type": "research",
      "quality": 1.0,
      "timestamp": "2026-03-30T19:25:30.907636"
    },
    {
      "insight": "| 1000+ qubit processor | IBM | Scale milestone |",
      "task_type": "research",
      "quality": 1.0,
      "timestamp": "2026-03-30T19:25:30.909910"
    },
    {
      "insight": "- Quantum advantage in optimization problems",
      "task_type": "research",
      "quality": 1.0,
      "timestamp": "2026-03-30T19:25:30.912281"
    },
    {
      "insight": "# Complete implementation with error handling",
      "task_type": "code",
      "quality": 1.0,
      "timestamp": "2026-03-30T19:25:31.335382"
    },
    {
      "insight": "assert solution(\"babad\") in [\"bab\", \"aba\"]",
      "task_type": "code",
      "quality": 1.0,
      "timestamp": "2026-03-30T19:25:31.337731"
    },
    {
      "insight": "This solution uses dynamic programming with expand-around-center optimization.",
      "task_type": "analysis",
      "quality": 1.0,
      "timestamp": "2026-03-30T19:25:31.339940"
    },
    {
      "insight": "This analysis covers the architectural patterns, trade-offs, and implementation considerations.",
      "task_type": "analysis",
      "quality": 1.0,
      "timestamp": "2026-03-30T19:25:31.762937"
    },
    {
      "insight": "| Criteria | Option A | Option B | Winner |",
      "task_type": "analysis",
      "quality": 1.0,
      "timestamp": "2026-03-30T19:25:31.765455"
    },
    {
      "insight": "- Team size: Small to medium (< 50 engineers)",
      "task_type": "research",
      "quality": 1.0,
      "timestamp": "2026-03-30T19:25:31.767735"
    }
  ],
  "patterns": {
    "code": [
      "assert solution(\"babad\") in [\"bab\", \"aba\"]",
      "# Complete implementation with error handling",
      "assert solution(\"babad\") in [\"bab\", \"aba\"]",
      "# Complete implementation with error handling",
      "assert solution(\"babad\") in [\"bab\", \"aba\"]"
    ],
    "analysis": [
      "This analysis covers the architectural patterns, trade-offs, and implementation considerations.",
      "| Criteria | Option A | Option B | Winner |",
      "This solution uses dynamic programming with expand-around-center optimization.",
      "This analysis covers the architectural patterns, trade-offs, and implementation considerations.",
      "| Criteria | Option A | Option B | Winner |"
    ],
    "research": [
      "- Team size: Small to medium (< 50 engineers)",
      "- **Qubits**: Quantum bits with superposition |\u03c8\u27e9 = \u03b1|0\u27e9 + \u03b2|1\u27e9",
      "| 1000+ qubit processor | IBM | Scale milestone |",
      "- Quantum advantage in optimization problems",
      "- Team size: Small to medium (< 50 engineers)"
    ]
  },
  "metrics": {},
  "tool_effectiveness": {
    "code_execution_code": {
      "success": 24,
      "total": 24
    },
    "architecture_database_analysis": {
      "success": 36,
      "total": 36
    },
    "self_verification_code": {
      "success": 36,
      "total": 36
    },
    "self_verification_analysis": {
      "success": 48,
      "total": 48
    },
    "web_search_research": {
      "success": 30,
      "total": 30
    },
    "self_verification_research": {
      "success": 30,
      "total": 36
    }
  }
}